SaturationEffect/__init__.pxd
SaturationEffect/__init__.py
SaturationEffect/example.py
SaturationEffect/hsl_c.c
SaturationEffect/saturation.c
SaturationEffect/saturation.cp39-win_amd64.pyd
SaturationEffect/saturation.pxd
SaturationEffect/saturation.pyx
SaturationEffect/setup_saturation.py
SaturationEffect/Assets/423px-Excitation_Purity.svg.png
SaturationEffect/Assets/background_checker.png
SaturationEffect/Assets/full_range_saturation.png
SaturationEffect/Assets/logo.png
SaturationEffect/Assets/logo_alpha.png
SaturationEffect/Assets/p1.png
SaturationEffect/Assets/skull_alpha.png
SaturationEffect/tests/profiling.py
SaturationEffect/tests/test_saturation.py
SaturationEffect-1.0.1.data/data/lib/site-packages/SaturationEffect/LICENSE
SaturationEffect-1.0.1.data/data/lib/site-packages/SaturationEffect/MANIFEST.in
SaturationEffect-1.0.1.data/data/lib/site-packages/SaturationEffect/README.md
SaturationEffect-1.0.1.data/data/lib/site-packages/SaturationEffect/__init__.pxd
SaturationEffect-1.0.1.data/data/lib/site-packages/SaturationEffect/__init__.py
SaturationEffect-1.0.1.data/data/lib/site-packages/SaturationEffect/example.py
SaturationEffect-1.0.1.data/data/lib/site-packages/SaturationEffect/hsl_c.c
SaturationEffect-1.0.1.data/data/lib/site-packages/SaturationEffect/pyproject.toml
SaturationEffect-1.0.1.data/data/lib/site-packages/SaturationEffect/requirements.txt
SaturationEffect-1.0.1.data/data/lib/site-packages/SaturationEffect/saturation.pxd
SaturationEffect-1.0.1.data/data/lib/site-packages/SaturationEffect/saturation.pyx
SaturationEffect-1.0.1.data/data/lib/site-packages/SaturationEffect/setup_saturation.py
SaturationEffect-1.0.1.data/data/lib/site-packages/SaturationEffect/Assets/423px-Excitation_Purity.svg.png
SaturationEffect-1.0.1.data/data/lib/site-packages/SaturationEffect/Assets/background_checker.png
SaturationEffect-1.0.1.data/data/lib/site-packages/SaturationEffect/Assets/full_range_saturation.png
SaturationEffect-1.0.1.dist-info/LICENSE
SaturationEffect-1.0.1.dist-info/METADATA
SaturationEffect-1.0.1.dist-info/WHEEL
SaturationEffect-1.0.1.dist-info/top_level.txt
SaturationEffect-1.0.1.dist-info/RECORD
